qx_game_bot/__init__.py
qx_game_bot/py.typed
qx_game_bot/adapters/cv/cv_color_matcher.py
qx_game_bot/adapters/cv/cv_template_matcher.py
qx_game_bot/adapters/framework/qx_game_bot_framework.py
qx_game_bot/adapters/mss/mss_screenshot.py
qx_game_bot/adapters/paddleocr/paddle_ocr.py
qx_game_bot/adapters/persistence/sqlite/db.py
qx_game_bot/adapters/persistence/sqlite/sqlite_task_repository.py
qx_game_bot/adapters/persistence/sqlite/models/task_model.py
qx_game_bot/adapters/pynput/pynput_action_player.py
qx_game_bot/adapters/pynput/pynput_global_hot_keys.py
qx_game_bot/adapters/pynput/pynput_keyboard_mouse_listener.py
qx_game_bot/core/domain/task.py
qx_game_bot/core/domain/value_objects/delay_action.py
qx_game_bot/core/domain/value_objects/img.py
qx_game_bot/core/domain/value_objects/key_press_action.py
qx_game_bot/core/domain/value_objects/key_release_action.py
qx_game_bot/core/domain/value_objects/key_tap_action.py
qx_game_bot/core/domain/value_objects/key_type_action.py
qx_game_bot/core/domain/value_objects/match_img_action.py
qx_game_bot/core/domain/value_objects/mouse_move_action.py
qx_game_bot/core/domain/value_objects/mouse_press_action.py
qx_game_bot/core/domain/value_objects/mouse_release_action.py
qx_game_bot/core/domain/value_objects/mouse_scroll_action.py
qx_game_bot/core/domain/value_objects/mouse_tap_action.py
qx_game_bot/core/ports/action_player.py
qx_game_bot/core/ports/color_matcher.py
qx_game_bot/core/ports/global_hot_keys.py
qx_game_bot/core/ports/keyboard_mouse_listener.py
qx_game_bot/core/ports/ocr.py
qx_game_bot/core/ports/screenshot.py
qx_game_bot/core/ports/task_repository.py
qx_game_bot/core/ports/template_matcher.py
qx_game_bot/core/usecases/get_task_usecase.py
qx_game_bot/core/usecases/img_ocr_usecase.py
qx_game_bot/core/usecases/match_all_screen_usecase.py
qx_game_bot/core/usecases/match_all_templates_usecase.py
qx_game_bot/core/usecases/match_screen_color_point_usecase.py
qx_game_bot/core/usecases/match_screen_usecase.py
qx_game_bot-0.1.4.dist-info/METADATA
qx_game_bot-0.1.4.dist-info/WHEEL
qx_game_bot-0.1.4.dist-info/RECORD
