Metadata-Version: 2.4
Name: qx-game-bot
Version: 0.1.4
Summary: Add your description here
Author-email: Yoki <yokiyuqian@gmail.com>
Requires-Python: >=3.11
Requires-Dist: mss>=10.0.0
Requires-Dist: opencv-contrib-python>=4.10.0.84
Requires-Dist: paddleocr>=2.9.1
Requires-Dist: paddlepaddle>=2.6.2
Requires-Dist: peewee>=3.17.8
Requires-Dist: pydantic>=2.10.4
Requires-Dist: pynput>=1.7.7
Requires-Dist: setuptools>=75.8.0
